clear_bow/__init__.py
clear_bow/_version.py
clear_bow/classifier.py
clear_bow-1.0.0.dist-info/licenses/LICENSE
clear_bow-1.0.0.dist-info/METADATA
clear_bow-1.0.0.dist-info/WHEEL
clear_bow-1.0.0.dist-info/top_level.txt
clear_bow-1.0.0.dist-info/RECORD
