Metadata-Version: 2.4
Name: clear-bow
Version: 1.0.0
Summary: A dictionary-based text classification library
Author-email: Sam Hardy <samhardyhey@gmail.com>
License: MIT License
Project-URL: Homepage, https://github.com/samhardyhey/clear-bow
Project-URL: Repository, https://github.com/samhardyhey/clear-bow.git
Project-URL: Issues, https://github.com/samhardyhey/clear-bow/issues
Keywords: python,text-classification,dictionary-based,classifier
Classifier: Development Status :: 4 - Beta
Classifier: Environment :: Console
Classifier: Intended Audience :: Developers
Classifier: License :: OSI Approved :: MIT License
Classifier: Programming Language :: Python :: 3
Classifier: Programming Language :: Python :: 3.9
Classifier: Programming Language :: Python :: 3.10
Classifier: Programming Language :: Python :: 3.11
Classifier: Programming Language :: Python :: 3.12
Classifier: Topic :: Software Development :: Libraries :: Python Modules
Classifier: Topic :: Software Development :: Quality Assurance
Requires-Python: >=3.9
License-File: LICENSE
Provides-Extra: dev
Requires-Dist: build==1.2.2.post1; extra == "dev"
Requires-Dist: tox==4.24.2; extra == "dev"
Requires-Dist: twine==6.1.0; extra == "dev"
Requires-Dist: setuptools_scm==8.0.0; extra == "dev"
Requires-Dist: pypi-cleanup==0.1.8; extra == "dev"
Requires-Dist: pytest==8.3.5; extra == "dev"
Requires-Dist: pytest-cov==4.1.0; extra == "dev"
Dynamic: license-file
